greek_normalisation/__init__.py
greek_normalisation/convert_files.py
greek_normalisation/norm_data.py
greek_normalisation/normalise.py
greek_normalisation/regexes.py
greek_normalisation/utils.py
greek_normalisation-0.5.1.dist-info/LICENSE
greek_normalisation-0.5.1.dist-info/METADATA
greek_normalisation-0.5.1.dist-info/WHEEL
greek_normalisation-0.5.1.dist-info/entry_points.txt
greek_normalisation-0.5.1.dist-info/top_level.txt
greek_normalisation-0.5.1.dist-info/RECORD
