Metadata-Version: 2.1
Name: greek-normalisation
Version: 0.5.1
Summary: Python 3 utilities for validating and normalising Ancient Greek text
Home-page: http://github.com/jtauber/greek-normalisation
Author: James Tauber
Author-email: jtauber@jtauber.com
License: MIT
Platform: UNKNOWN
Classifier: Development Status :: 4 - Beta
Classifier: License :: OSI Approved :: MIT License
Classifier: Programming Language :: Python :: 3.6
Classifier: Programming Language :: Python :: 3.7
Classifier: Programming Language :: Python :: 3.8
Classifier: Topic :: Text Processing :: Linguistic
